pypowerbifix
