Metadata-Version: 1.0
Name: pypowerbifix
Version: 0.29
Summary: A python library for Microsoft's PowerBI
Home-page: http://github.com/cmberryau/pypowerbi
Author: Chris Berry
Author-email: chris@chrisberry.com.au
License: MIT
Platform: UNKNOWN
